arcfish/__init__.py
arcfish-1.0.1.dist-info/licenses/LICENSE
arcfish-1.0.1.dist-info/METADATA
arcfish-1.0.1.dist-info/WHEEL
arcfish-1.0.1.dist-info/entry_points.txt
arcfish-1.0.1.dist-info/top_level.txt
arcfish-1.0.1.dist-info/RECORD
