Metadata-Version: 2.4
Name: arcfish
Version: 1.0.1
Summary: Accurate and robust 3D genome feature discovery from chromatin tracing data
Author-email: Hongyu Yu <hongyuyu@unc.edu>
Project-URL: Source, https://github.com/hyuyu104/ArcFISH
Project-URL: Docs, https://hyuyu104.github.io/ArcFISH
Classifier: Programming Language :: Python :: 3
Classifier: Operating System :: OS Independent
Requires-Python: >=3.12
License-File: LICENSE
Requires-Dist: numpy>=1.26.4
Requires-Dist: pandas>=2.2.1
Requires-Dist: scipy>=1.12.0
Requires-Dist: matplotlib>=3.8.3
Requires-Dist: seaborn>=0.13.2
Requires-Dist: statsmodels==0.14.1
Requires-Dist: scikit-learn>=1.4.1
Requires-Dist: anndata==0.10.8
Requires-Dist: dask==2025.1.0
Requires-Dist: requests>=2.31.0
Provides-Extra: docs
Requires-Dist: sphinx==8.1.3; extra == "docs"
Requires-Dist: pydata-sphinx-theme==0.16.1; extra == "docs"
Requires-Dist: sphinxcontrib-napoleon==0.7; extra == "docs"
Requires-Dist: myst-parser==4.0.0; extra == "docs"
Requires-Dist: sphinx_plotly_directive==0.1.3; extra == "docs"
Requires-Dist: sphinx_design==0.6.1; extra == "docs"
Requires-Dist: sphinx-tabs==3.4.7; extra == "docs"
Requires-Dist: sphinx-copybutton==0.5.2; extra == "docs"
Requires-Dist: nbsphinx==0.9.7; extra == "docs"
Requires-Dist: pypandoc==1.16; extra == "docs"
Requires-Dist: ipython==9.7.0; extra == "docs"
Dynamic: license-file
